dicom_numpy/__init__.py
dicom_numpy/combine_slices.py
dicom_numpy/exceptions.py
dicom_numpy/version.py
dicom_numpy/zip_archive.py
dicom_numpy-0.6.5.dist-info/LICENSE.txt
dicom_numpy-0.6.5.dist-info/METADATA
dicom_numpy-0.6.5.dist-info/WHEEL
dicom_numpy-0.6.5.dist-info/top_level.txt
dicom_numpy-0.6.5.dist-info/RECORD
