Metadata-Version: 2.1
Name: dicom-numpy
Version: 0.6.5
Summary: Extract image data into a 3D numpy array from a set of DICOM files.
Home-page: https://github.com/innolitics/dicom-numpy
Author: Innolitics, LLC
Author-email: info@innolitics.com
License: MIT
Keywords: dicom numpy
Classifier: Development Status :: 5 - Production/Stable
Classifier: Intended Audience :: Developers
Classifier: Intended Audience :: Healthcare Industry
Classifier: Topic :: Software Development :: Build Tools
Classifier: Topic :: Scientific/Engineering :: Medical Science Apps.
Classifier: License :: OSI Approved :: MIT License
Classifier: Programming Language :: Python :: 3
Classifier: Programming Language :: Python :: 3.6
Classifier: Programming Language :: Python :: 3.7
Classifier: Programming Language :: Python :: 3.8
Classifier: Programming Language :: Python :: 3.9
Requires-Python: >= 3.6
License-File: LICENSE.txt
Requires-Dist: pydicom (>=1.0)
Requires-Dist: numpy
Provides-Extra: dev
Requires-Dist: check-manifest ; extra == 'dev'
Requires-Dist: sphinx ; extra == 'dev'
Requires-Dist: sphinx-autobuild ; extra == 'dev'
Provides-Extra: test
Requires-Dist: coverage ; extra == 'test'
Requires-Dist: pytest ; extra == 'test'
